hbsc_utils/__init__.py
hbsc_utils/cat.py
hbsc_utils/rpc.py
hbsc_utils/spends.py
hbsc_utils-0.2.1.dist-info/LICENSE
hbsc_utils-0.2.1.dist-info/WHEEL
hbsc_utils-0.2.1.dist-info/METADATA
hbsc_utils-0.2.1.dist-info/RECORD
